[{"name":"Rescue Ship - Li Qing Jao","systemName":"Sol","distanceToArrival":495.853502,"type":"Mega ship","allegiance":"Federation","government":"Democracy","economy":"Rescue","faction":"Mother Gaia","systemsecurity":"High","systempopulation":22780919531,"powerplaystate":"Control","powers":"Zachary Hudson","x":0.0,"y":0.0,"z":0.0,"marketId":128977009,"economies":"Rescue","systemstate":"None"},{"name":"Noakes Market","systemName":"GCRV 2743","distanceToArrival":424.875621,"type":"Orbis Starport","allegiance":"Independent","government":"Dictatorship","economy":"Agriculture","faction":"New GCRV 2743 Order","systemsecurity":"High","systempopulation":4075626783,"powerplaystate":"Control","powers":"Zachary Hudson","x":-69.375,"y":28.59375,"z":-93.03125,"marketId":3226581504,"economies":"Agriculture","systemstate":"None"},{"name":"Reilly Dock","systemName":"LTT 15449","distanceToArrival":782.313616,"type":"Orbis Starport","allegiance":"Federation","government":"Democracy","economy":"Agriculture","faction":"Infinite Corporation","systemsecurity":"High","systempopulation":6791886799,"powerplaystate":"Control","powers":"Zachary Hudson","x":-55.28125,"y":20.5,"z":42.15625,"marketId":3229021184,"economies":"Agriculture","systemstate":"None"},{"name":"Chiao City","systemName":"GCRV 2743","distanceToArrival":81.779759,"type":"Orbis Starport","allegiance":"Independent","government":"Dictatorship","economy":"Refinery","faction":"New GCRV 2743 Order","systemsecurity":"High","systempopulation":4075626783,"powerplaystate":"Control","powers":"Zachary Hudson","x":-69.375,"y":28.59375,"z":-93.03125,"marketId":3226582016,"economies":"Refinery","systemstate":"None"},{"name":"Roentgen Port","systemName":"LTT 15449","distanceToArrival":783.284525,"type":"Orbis Starport","allegiance":"Federation","government":"Democracy","economy":"Agriculture","faction":"Infinite Corporation","systemsecurity":"High","systempopulation":6791886799,"powerplaystate":"Control","powers":"Zachary Hudson","x":-55.28125,"y":20.5,"z":42.15625,"marketId":3229021440,"economies":"Agriculture","systemstate":"None"},{"name":"Dalton Gateway","systemName":"LHS 3447","distanceToArrival":92060.850914,"type":"Orbis Starport","allegiance":"Pilots Federation","government":"Democracy","economy":"Agriculture","faction":"Pilots' Federation Local Branch","systemsecurity":"High","systempopulation":1148257346,"powerplaystate":"Control","powers":"Zachary Hudson","x":-43.1875,"y":-5.28125,"z":56.15625,"marketId":3230571520,"economies":"Agriculture","systemstate":"None"},{"name":"Borisenko Dock","systemName":"16 Cygni","distanceToArrival":171880.388828,"type":"Orbis Starport","allegiance":"Federation","government":"Democracy","economy":"Industrial","faction":"16 Cygni Liberals","systemsecurity":"High","systempopulation":6482960270,"powerplaystate":"Control","powers":"Zachary Hudson","x":-66.5625,"y":15.53125,"z":7.5,"marketId":3226658304,"economies":"Industrial","systemstate":"None"},{"name":"Jernigan Orbital","systemName":"Lalande 39866","distanceToArrival":4957.401786,"type":"Orbis Starport","allegiance":"Federation","government":"Democracy","economy":"Agriculture","faction":"Progressive Party of Lalande 39866","systemsecurity":"High","systempopulation":1686391822,"powerplaystate":"Control","powers":"Zachary Hudson","x":-43.875,"y":-22.46875,"z":35.28125,"marketId":3228918528,"economies":"Agriculture","systemstate":"None"},{"name":"Dana Terminal","systemName":"Wolf 867","distanceToArrival":329.821111,"type":"Orbis Starport","allegiance":"Federation","government":"Democracy","economy":"Agriculture","faction":"United Wolf 867 Values Party","systemsecurity":"High","systempopulation":1260537093,"powerplaystate":"Control","powers":"Zachary Hudson","x":-45.375,"y":-4.09375,"z":23.84375,"marketId":3228921344,"economies":"Agriculture","systemstate":"None"},{"name":"Tokarev Hub","systemName":"Epsilon Scorpii","distanceToArrival":3396.362211,"type":"Orbis Starport","allegiance":"Federation","government":"Democracy","economy":"Agriculture","faction":"People's Epsilon Scorpii Resistance","systemsecurity":"High","systempopulation":7936392052,"powerplaystate":"Control","powers":"Zachary Hudson","x":11.875,"y":6.625,"z":62.21875,"marketId":3230486272,"economies":"Agriculture","systemstate":"None"},{"name":"Khrunov City","systemName":"Epsilon Scorpii","distanceToArrival":2566.401167,"type":"Coriolis Starport","allegiance":"Federation","government":"Democracy","economy":"Agriculture","faction":"People's Epsilon Scorpii Resistance","systemsecurity":"High","systempopulation":7936392052,"powerplaystate":"Control","powers":"Zachary Hudson","x":11.875,"y":6.625,"z":62.21875,"marketId":3230486016,"economies":"Agriculture","systemstate":"None"},{"name":"Lindstrand Orbital","systemName":"LTT 9472","distanceToArrival":1086.369505,"type":"Orbis Starport","allegiance":"Empire","government":"Patronage","economy":"Agriculture","faction":"Xhosag Imperial Society","systemsecurity":"High","systempopulation":6872529818,"powerplaystate":"Control","powers":"Zachary Hudson","x":44.5625,"y":-108.9375,"z":60.8125,"marketId":3225535744,"economies":"Agriculture","systemstate":"Expansion"},{"name":"Parmitano Station","systemName":"Parutis","distanceToArrival":1335.533713,"type":"Orbis Starport","allegiance":"Federation","government":"Corporate","economy":"Refinery","faction":"Parutis Fortune Ltd","systemsecurity":"High","systempopulation":3893844490,"powerplaystate":"Control","powers":"Zachary Hudson","x":0.71875,"y":10.71875,"z":33.28125,"marketId":3228774656,"economies":"Refinery","systemstate":"None"},{"name":"Payette Market","systemName":"16 Cygni","distanceToArrival":172728.230349,"type":"Orbis Starport","allegiance":"Federation","government":"Democracy","economy":"Agriculture","faction":"16 Cygni Liberals","systemsecurity":"High","systempopulation":6482960270,"powerplaystate":"Control","powers":"Zachary Hudson","x":-66.5625,"y":15.53125,"z":7.5,"marketId":3226657280,"economies":"Agriculture","systemstate":"None"},{"name":"Helms Hub","systemName":"Alpha Fornacis","distanceToArrival":12528.677209,"type":"Orbis Starport","allegiance":"Federation","government":"Corporate","economy":"Refinery","faction":"Alpha Fornacis Allied Corporation","systemsecurity":"High","systempopulation":5043700924,"powerplaystate":"Control","powers":"Zachary Hudson","x":16.9375,"y":-39.625,"z":-17.3125,"marketId":3223691520,"economies":"Refinery","systemstate":"Expansion"},{"name":"Dzhanibekov Hub","systemName":"Lalande 39866","distanceToArrival":367.513152,"type":"Orbis Starport","allegiance":"Federation","government":"Democracy","economy":"Industrial","faction":"Progressive Party of Lalande 39866","systemsecurity":"High","systempopulation":1686391822,"powerplaystate":"Control","powers":"Zachary Hudson","x":-43.875,"y":-22.46875,"z":35.28125,"marketId":3228919040,"economies":"Industrial","systemstate":"None"},{"name":"Carpini Station","systemName":"Mantxe","distanceToArrival":507.680476,"type":"Orbis Starport","allegiance":"Federation","government":"Corporate","economy":"Terraforming","faction":"Mantxe Comms Exchange","systemsecurity":"High","systempopulation":2221160701,"powerplaystate":"Control","powers":"Zachary Hudson","x":-3.28125,"y":-8.375,"z":58.75,"marketId":3230481664,"economies":"Terraforming","systemstate":"None"},{"name":"Bennett Port","systemName":"Alpha Fornacis","distanceToArrival":12424.789469,"type":"Orbis Starport","allegiance":"Federation","government":"Corporate","economy":"Refinery","faction":"Alpha Fornacis Allied Corporation","systemsecurity":"High","systempopulation":5043700924,"powerplaystate":"Control","powers":"Zachary Hudson","x":16.9375,"y":-39.625,"z":-17.3125,"marketId":3223691264,"economies":"Refinery","systemstate":"Expansion"},{"name":"Siemens Orbital","systemName":"16 Cygni","distanceToArrival":172496.194966,"type":"Orbis Starport","allegiance":"Federation","government":"Democracy","economy":"Industrial","faction":"16 Cygni Liberals","systemsecurity":"High","systempopulation":6482960270,"powerplaystate":"Control","powers":"Zachary Hudson","x":-66.5625,"y":15.53125,"z":7.5,"marketId":3226657792,"economies":"Industrial","systemstate":"None"},{"name":"de Sousa Ring","systemName":"Mantxe","distanceToArrival":359.038051,"type":"Orbis Starport","allegiance":"Federation","government":"Corporate","economy":"Agriculture","faction":"Mantxe Comms Exchange","systemsecurity":"High","systempopulation":2221160701,"powerplaystate":"Control","powers":"Zachary Hudson","x":-3.28125,"y":-8.375,"z":58.75,"marketId":3230481408,"economies":"Agriculture","systemstate":"None"},{"name":"Hoften Port","systemName":"Wadir","distanceToArrival":2988.4574,"type":"Coriolis Starport","allegiance":"Independent","government":"Feudal","economy":"Terraforming","faction":"The Dukes of Mikunn","systemsecurity":"Medium","systempopulation":146479,"powerplaystate":"Control","powers":"Zachary Hudson","x":-42.9375,"y":-66.6875,"z":139.84375,"marketId":3226317056,"economies":"Terraforming","systemstate":"None"},{"name":"Saunders Dock","systemName":"Mislika","distanceToArrival":5862.670279,"type":"Ocellus Starport","allegiance":"Federation","government":"Corporate","economy":"Industrial","faction":"Andlit Co","systemsecurity":"Medium","systempopulation":2445697,"powerplaystate":"Control","powers":"Zachary Hudson","x":-99.0625,"y":-3.40625,"z":3.125,"marketId":3226723072,"economies":"Industrial","systemstate":"None"},{"name":"Pontes Terminal","systemName":"Mariyacoch","distanceToArrival":23.299895,"type":"Ocellus Starport","allegiance":"Independent","government":"Feudal","economy":"Refinery","faction":"Nobles of NLTT 51200","systemsecurity":"High","systempopulation":1546608805,"powerplaystate":"Control","powers":"Zachary Hudson","x":-64.28125,"y":-41.78125,"z":27.9375,"marketId":3224178944,"economies":"Refinery","systemstate":"None"},{"name":"Chamitoff Dock","systemName":"Mariyacoch","distanceToArrival":4.66276,"type":"Ocellus Starport","allegiance":"Independent","government":"Feudal","economy":"Refinery","faction":"Nobles of NLTT 51200","systemsecurity":"High","systempopulation":1546608805,"powerplaystate":"Control","powers":"Zachary Hudson","x":-64.28125,"y":-41.78125,"z":27.9375,"marketId":3224178688,"economies":"Refinery","systemstate":"None"},{"name":"Savitskaya Station","systemName":"Mariyacoch","distanceToArrival":13.506666,"type":"Orbis Starport","allegiance":"Independent","government":"Feudal","economy":"Agriculture","faction":"Nobles of NLTT 51200","systemsecurity":"High","systempopulation":1546608805,"powerplaystate":"Control","powers":"Zachary Hudson","x":-64.28125,"y":-41.78125,"z":27.9375,"marketId":3224178432,"economies":"Agriculture","systemstate":"None"},{"name":"Worlidge Terminal","systemName":"LHS 3447","distanceToArrival":92020.59429,"type":"Coriolis Starport","allegiance":"Federation","government":"Corporate","economy":"Extraction","faction":"LHS 3447 Dynamic & Co","systemsecurity":"High","systempopulation":1148257346,"powerplaystate":"Control","powers":"Zachary Hudson","x":-43.1875,"y":-5.28125,"z":56.15625,"marketId":3230572032,"economies":"Extraction","systemstate":"None"},{"name":"Ramelli Dock","systemName":"Adeo","distanceToArrival":90.187239,"type":"Orbis Starport","allegiance":"Independent","government":"Feudal","economy":"Refinery","faction":"Marquis du Slavanibo","systemsecurity":"High","systempopulation":8257499087,"powerplaystate":"Control","powers":"Zachary Hudson","x":-81.625,"y":31.40625,"z":27.1875,"marketId":3226847232,"economies":"Refinery","systemstate":"None"},{"name":"Euler Hub","systemName":"Atropos","distanceToArrival":61.904019,"type":"Orbis Starport","allegiance":"Federation","government":"Corporate","economy":"Refinery","faction":"Atropos & Co","systemsecurity":"High","systempopulation":4373937513,"powerplaystate":"Control","powers":"Zachary Hudson","x":41.40625,"y":-29.6875,"z":-27.625,"marketId":3223643904,"economies":"Refinery","systemstate":"Boom"},{"name":"Spedding Orbital","systemName":"Atropos","distanceToArrival":62.293547,"type":"Orbis Starport","allegiance":"Federation","government":"Corporate","economy":"Refinery","faction":"Atropos & Co","systemsecurity":"High","systempopulation":4373937513,"powerplaystate":"Control","powers":"Zachary Hudson","x":41.40625,"y":-29.6875,"z":-27.625,"marketId":3223643648,"economies":"Refinery","systemstate":"Boom"},{"name":"vo Market","systemName":"Atropos","distanceToArrival":191.541441,"type":"Orbis Starport","allegiance":"Federation","government":"Corporate","economy":"Agriculture","faction":"Atropos & Co","systemsecurity":"High","systempopulation":4373937513,"powerplaystate":"Control","powers":"Zachary Hudson","x":41.40625,"y":-29.6875,"z":-27.625,"marketId":3223643136,"economies":"Agriculture","systemstate":"Boom"},{"name":"Foda Port","systemName":"Adeo","distanceToArrival":66.91003,"type":"Orbis Starport","allegiance":"Independent","government":"Feudal","economy":"Refinery","faction":"Marquis du Slavanibo","systemsecurity":"High","systempopulation":8257499087,"powerplaystate":"Control","powers":"Zachary Hudson","x":-81.625,"y":31.40625,"z":27.1875,"marketId":3226846976,"economies":"Refinery","systemstate":"None"},{"name":"Doi City","systemName":"Alpha Fornacis","distanceToArrival":12567.293091,"type":"Orbis Starport","allegiance":"Empire","government":"Corporate","economy":"Agriculture","faction":"East India Company","systemsecurity":"High","systempopulation":5043700924,"powerplaystate":"Control","powers":"Zachary Hudson","x":16.9375,"y":-39.625,"z":-17.3125,"marketId":3223690752,"economies":"Agriculture","systemstate":"Expansion"},{"name":"Binet Port","systemName":"LTT 15449","distanceToArrival":16.411996,"type":"Orbis Starport","allegiance":"Federation","government":"Democracy","economy":"Industrial","faction":"Infinite Corporation","systemsecurity":"High","systempopulation":6791886799,"powerplaystate":"Control","powers":"Zachary Hudson","x":-55.28125,"y":20.5,"z":42.15625,"marketId":3229021696,"economies":"Industrial","systemstate":"None"},{"name":"Gagarin Enterprise","systemName":"Epsilon Scorpii","distanceToArrival":449.918376,"type":"Orbis Starport","allegiance":"Federation","government":"Democracy","economy":"Industrial","faction":"People's Epsilon Scorpii Resistance","systemsecurity":"High","systempopulation":7936392052,"powerplaystate":"Control","powers":"Zachary Hudson","x":11.875,"y":6.625,"z":62.21875,"marketId":3230486784,"economies":"Industrial","systemstate":"None"},{"name":"Fleming City","systemName":"Mulachi","distanceToArrival":594381.094774,"type":"Orbis Starport","allegiance":"Federation","government":"Democracy","economy":"Industrial","faction":"Workers of Santy Independents","systemsecurity":"High","systempopulation":4407803057,"powerplaystate":"Control","powers":"Zachary Hudson","x":6.25,"y":-5.78125,"z":35.9375,"marketId":3228893184,"economies":"Industrial","systemstate":"None"},{"name":"Binnie Orbital","systemName":"Shoujeman","distanceToArrival":115.836604,"type":"Coriolis Starport","allegiance":"Alliance","government":"Patronage","economy":"Refinery","faction":"LHS 2541 Alliance Combine","systemsecurity":"Medium","systempopulation":506560,"powerplaystate":"Control","powers":"Zachary Hudson","x":12.4375,"y":30.90625,"z":9.15625,"marketId":3228779008,"economies":"Refinery,Extraction","systemstate":"Boom"},{"name":"Minne Orbital","systemName":"Wolf 25","distanceToArrival":285.063924,"type":"Orbis Starport","allegiance":"Independent","government":"Cooperative","economy":"Agriculture","faction":"Hutton Orbital Truckers Co-Operative","systemsecurity":"Medium","systempopulation":1317590,"powerplaystate":"Control","powers":"Zachary Hudson","x":-11.0625,"y":-20.46875,"z":-7.125,"marketId":128124152,"economies":"Agriculture","systemstate":"Boom,Civil Liberty"},{"name":"Clark Terminal","systemName":"Mulachi","distanceToArrival":594476.073303,"type":"Orbis Starport","allegiance":"Federation","government":"Democracy","economy":"Agriculture","faction":"Revolutionary Mulachi for Equality","systemsecurity":"High","systempopulation":4407803057,"powerplaystate":"Control","powers":"Zachary Hudson","x":6.25,"y":-5.78125,"z":35.9375,"marketId":3228892672,"economies":"Agriculture","systemstate":"None"},{"name":"Gernhardt Terminal","systemName":"Mulachi","distanceToArrival":594372.445569,"type":"Orbis Starport","allegiance":"Federation","government":"Democracy","economy":"Industrial","faction":"Revolutionary Mulachi for Equality","systemsecurity":"High","systempopulation":4407803057,"powerplaystate":"Control","powers":"Zachary Hudson","x":6.25,"y":-5.78125,"z":35.9375,"marketId":3228893440,"economies":"Industrial","systemstate":"None"},{"name":"Northrop Port","systemName":"16 Cygni","distanceToArrival":173407.432229,"type":"Orbis Starport","allegiance":"Federation","government":"Democracy","economy":"Industrial","faction":"16 Cygni Liberals","systemsecurity":"High","systempopulation":6482960270,"powerplaystate":"Control","powers":"Zachary Hudson","x":-66.5625,"y":15.53125,"z":7.5,"marketId":3226658560,"economies":"Industrial","systemstate":"None"},{"name":"Rushd Ring","systemName":"39 Serpentis","distanceToArrival":1309.753192,"type":"Orbis Starport","allegiance":"Federation","government":"Democracy","economy":"Tourism","faction":"39 Serpentis Progressive Party","systemsecurity":"High","systempopulation":6723043084,"powerplaystate":"Control","powers":"Zachary Hudson","x":-16.46875,"y":39.875,"z":36.59375,"marketId":3228921088,"economies":"Tourism","systemstate":"None"},{"name":"Cormack Dock","systemName":"GCRV 2743","distanceToArrival":61.057827,"type":"Orbis Starport","allegiance":"Independent","government":"Dictatorship","economy":"Refinery","faction":"New GCRV 2743 Order","systemsecurity":"High","systempopulation":4075626783,"powerplaystate":"Control","powers":"Zachary Hudson","x":-69.375,"y":28.59375,"z":-93.03125,"marketId":3226581760,"economies":"Refinery","systemstate":"None"},{"name":"Porges Horizons","systemName":"G 250-34","distanceToArrival":36.278837,"type":"Coriolis Starport","allegiance":"Federation","government":"Democracy","economy":"High Tech","faction":"Blood Brothers from Alrai","systemsecurity":"High","systempopulation":30698753,"powerplaystate":"Control","powers":"Zachary Hudson","x":-27.28125,"y":25.90625,"z":-44.5,"marketId":3228166400,"economies":"High Tech,Refinery","systemstate":"None"},{"name":"Mori Terminal","systemName":"Vega","distanceToArrival":3761.957522,"type":"Coriolis Starport","allegiance":"Federation","government":"Democracy","economy":"Agriculture","faction":"Vega Independents","systemsecurity":"High","systempopulation":600017409,"powerplaystate":"Control","powers":"Zachary Hudson","x":-21.90625,"y":8.125,"z":9.0,"marketId":128149752,"economies":"Agriculture","systemstate":"None"},{"name":"Akers Market","systemName":"Mulachi","distanceToArrival":548.953396,"type":"Orbis Starport","allegiance":"Federation","government":"Democracy","economy":"Agriculture","faction":"Revolutionary Mulachi for Equality","systemsecurity":"High","systempopulation":4407803057,"powerplaystate":"Control","powers":"Zachary Hudson","x":6.25,"y":-5.78125,"z":35.9375,"marketId":3228892416,"economies":"Agriculture","systemstate":"None"},{"name":"Alvarado Ring","systemName":"LHS 3885","distanceToArrival":722.701611,"type":"Coriolis Starport","allegiance":"Federation","government":"Corporate","economy":"High Tech","faction":"Izumo Heavy Industries Ltd","systemsecurity":"High","systempopulation":17142721,"powerplaystate":"Control","powers":"Zachary Hudson","x":-7.03125,"y":-24.28125,"z":8.90625,"marketId":3228916736,"economies":"High Tech,Refinery","systemstate":"Boom"},{"name":"Goddard City","systemName":"Lalande 39866","distanceToArrival":207.968228,"type":"Orbis Starport","allegiance":"Federation","government":"Democracy","economy":"Agriculture","faction":"Progressive Party of Lalande 39866","systemsecurity":"High","systempopulation":1686391822,"powerplaystate":"Control","powers":"Zachary Hudson","x":-43.875,"y":-22.46875,"z":35.28125,"marketId":3228918272,"economies":"Agriculture","systemstate":"None"},{"name":"Gonnessiat Dock","systemName":"LTT 9472","distanceToArrival":455.184078,"type":"Orbis Starport","allegiance":"Independent","government":"Cooperative","economy":"Agriculture","faction":"Celestial Light Brigade","systemsecurity":"High","systempopulation":6872529818,"powerplaystate":"Control","powers":"Zachary Hudson","x":44.5625,"y":-108.9375,"z":60.8125,"marketId":3225535488,"economies":"Agriculture","systemstate":"Expansion"},{"name":"Boulton Station","systemName":"Venetic","distanceToArrival":316.565894,"type":"Ocellus Starport","allegiance":"Federation","government":"Democracy","economy":"Refinery","faction":"Movement for Venetic Progressive Party","systemsecurity":"High","systempopulation":12496303,"powerplaystate":"Control","powers":"Zachary Hudson","x":-68.4375,"y":14.8125,"z":35.0625,"marketId":3226662912,"economies":"Refinery,Industrial","systemstate":"None"},{"name":"Agassiz City","systemName":"Aornum","distanceToArrival":586.811188,"type":"Ocellus Starport","allegiance":"Federation","government":"Democracy","economy":"Refinery","faction":"Aornum Republic Party","systemsecurity":"High","systempopulation":945888291,"powerplaystate":"Control","powers":"Zachary Hudson","x":7.5625,"y":-34.90625,"z":31.625,"marketId":3224227328,"economies":"Refinery","systemstate":"Boom"},{"name":"Heck Reserve","systemName":"Skardee","distanceToArrival":36.803585,"type":"Coriolis Starport","allegiance":"Federation","government":"Corporate","economy":"Agriculture","faction":"Ice Storm Squadron","systemsecurity":"Low","systempopulation":8828,"powerplaystate":"Control","powers":"Zachary Hudson","x":89.46875,"y":-3.5625,"z":-2.625,"marketId":128138488,"economies":"Agriculture","systemstate":"Investment"},{"name":"Herbert Dock","systemName":"Wolf 906","distanceToArrival":505.936358,"type":"Coriolis Starport","allegiance":"Federation","government":"Democracy","economy":"High Tech","faction":"Values Party of Wolf 906","systemsecurity":"Medium","systempopulation":5736364,"powerplaystate":"Control","powers":"Zachary Hudson","x":-27.28125,"y":-25.09375,"z":28.78125,"marketId":3224185344,"economies":"High Tech,Refinery","systemstate":"Boom,Civil Liberty"},{"name":"Tun's Wart","systemName":"Tun","distanceToArrival":231.115544,"type":"Orbis Starport","allegiance":"Federation","government":"Democracy","economy":"Agriculture","faction":"People's Tun for Equality","systemsecurity":"Medium","systempopulation":500000,"powerplaystate":"Control","powers":"Zachary Hudson","x":-47.96875,"y":20.96875,"z":-17.53125,"marketId":128117752,"economies":"Agriculture","systemstate":"Boom"},{"name":"Franklin Ring","systemName":"Groombridge 1618","distanceToArrival":931.749591,"type":"Orbis Starport","allegiance":"Independent","government":"Dictatorship","economy":"Industrial","faction":"Nationalists of Groombridge 1618","systemsecurity":"High","systempopulation":5914893483,"powerplaystate":"Control","powers":"Zachary Hudson","x":-2.34375,"y":12.625,"z":-9.34375,"marketId":3229019648,"economies":"Industrial","systemstate":"Boom"},{"name":"Cady Market","systemName":"Groombridge 1618","distanceToArrival":169.885365,"type":"Orbis Starport","allegiance":"Independent","government":"Dictatorship","economy":"Agriculture","faction":"Nationalists of Groombridge 1618","systemsecurity":"High","systempopulation":5914893483,"powerplaystate":"Control","powers":"Zachary Hudson","x":-2.34375,"y":12.625,"z":-9.34375,"marketId":3229018880,"economies":"Agriculture","systemstate":"Boom"},{"name":"Yaping Enterprise","systemName":"LHS 3447","distanceToArrival":92059.50565,"type":"Coriolis Starport","allegiance":"Federation","government":"Corporate","economy":"Extraction","faction":"LHS 3447 Dynamic & Co","systemsecurity":"High","systempopulation":1148257346,"powerplaystate":"Control","powers":"Zachary Hudson","x":-43.1875,"y":-5.28125,"z":56.15625,"marketId":3230572288,"economies":"Extraction","systemstate":"None"},{"name":"Darlton Orbital","systemName":"Phra Mool","distanceToArrival":371.77143,"type":"Coriolis Starport","allegiance":"Empire","government":"Patronage","economy":"Refinery","faction":"Phra Mool Patrons of Law","systemsecurity":"Medium","systempopulation":1490261,"powerplaystate":"Control","powers":"Zachary Hudson","x":25.0625,"y":-19.96875,"z":58.875,"marketId":3230714880,"economies":"Refinery,Industrial","systemstate":"Boom"},{"name":"Haxel Port","systemName":"LTT 15574","distanceToArrival":615.518542,"type":"Ocellus Starport","allegiance":"Federation","government":"Democracy","economy":"Industrial","faction":"Democrats of LTT 15574","systemsecurity":"High","systempopulation":10791203,"powerplaystate":"Control","powers":"Zachary Hudson","x":-55.9375,"y":1.9375,"z":63.59375,"marketId":3230440960,"economies":"Industrial,Extraction","systemstate":"Boom,Civil Liberty"},{"name":"Kepler Orbital","systemName":"Atropos","distanceToArrival":36.228818,"type":"Orbis Starport","allegiance":"Federation","government":"Corporate","economy":"Refinery","faction":"Atropos & Co","systemsecurity":"High","systempopulation":4373937513,"powerplaystate":"Control","powers":"Zachary Hudson","x":41.40625,"y":-29.6875,"z":-27.625,"marketId":3223643392,"economies":"Refinery","systemstate":"Boom"},{"name":"Schweickart City","systemName":"Parutis","distanceToArrival":838.905734,"type":"Orbis Starport","allegiance":"Federation","government":"Democracy","economy":"Agriculture","faction":"Labour of Parutis","systemsecurity":"High","systempopulation":3893844490,"powerplaystate":"Control","powers":"Zachary Hudson","x":0.71875,"y":10.71875,"z":33.28125,"marketId":3228773888,"economies":"Agriculture","systemstate":"None"},{"name":"Bluford Orbital","systemName":"LHS 3447","distanceToArrival":2100.544703,"type":"Orbis Starport","allegiance":"Pilots Federation","government":"Democracy","economy":"Agriculture","faction":"Pilots' Federation Local Branch","systemsecurity":"High","systempopulation":1148257346,"powerplaystate":"Control","powers":"Zachary Hudson","x":-43.1875,"y":-5.28125,"z":56.15625,"marketId":128673074,"economies":"Agriculture","systemstate":"None"},{"name":"Houssay Terminal","systemName":"Gliese 868","distanceToArrival":155.260952,"type":"Orbis Starport","allegiance":"Federation","government":"Corporate","economy":"Agriculture","faction":"Izumo Heavy Industries Ltd","systemsecurity":"High","systempopulation":8508724066,"powerplaystate":"Control","powers":"Zachary Hudson","x":-7.375,"y":-38.96875,"z":19.5,"marketId":3224116480,"economies":"Agriculture","systemstate":"Boom"},{"name":"Chretien Terminal","systemName":"LHS 1197","distanceToArrival":427.479286,"type":"Coriolis Starport","allegiance":"Federation","government":"Democracy","economy":"High Tech","faction":"Independent LHS 1197 Values Party","systemsecurity":"High","systempopulation":13662847,"powerplaystate":"Control","powers":"Zachary Hudson","x":2.5625,"y":-42.8125,"z":-1.625,"marketId":3224185600,"economies":"High Tech,Refinery","systemstate":"None"},{"name":"Herschel Terminal","systemName":"Tsohock","distanceToArrival":1077.24653,"type":"Coriolis Starport","allegiance":"Empire","government":"Corporate","economy":"Industrial","faction":"Tsohock Legal Interstellar","systemsecurity":"Medium","systempopulation":3582807,"powerplaystate":"Control","powers":"Zachary Hudson","x":105.125,"y":-40.6875,"z":25.875,"marketId":3224947968,"economies":"Industrial","systemstate":"Boom"},{"name":"Elgin Terminal","systemName":"LHS 3577","distanceToArrival":308.325983,"type":"Coriolis Starport","allegiance":"Federation","government":"Democracy","economy":"High Tech","faction":"Democrats of Korwei","systemsecurity":"High","systempopulation":16095029,"powerplaystate":"Control","powers":"Zachary Hudson","x":-40.59375,"y":0.625,"z":3.96875,"marketId":3228856064,"economies":"High Tech,Refinery","systemstate":"Boom"},{"name":"Neville Horizons","systemName":"Kaushpoos","distanceToArrival":8.361349,"type":"Coriolis Starport","allegiance":"Alliance","government":"Patronage","economy":"High Tech","faction":"Kaushpoos Pro-Alliance Union","systemsecurity":"High","systempopulation":11419718,"powerplaystate":"Control","powers":"Zachary Hudson","x":-1.90625,"y":65.1875,"z":-79.65625,"marketId":3229104896,"economies":"High Tech,Refinery","systemstate":"Boom"},{"name":"Wedge Market","systemName":"NLTT 46621","distanceToArrival":3026.922796,"type":"Orbis Starport","allegiance":"Independent","government":"Feudal","economy":"Agriculture","faction":"Leaders of Eos","systemsecurity":"High","systempopulation":4647443345,"powerplaystate":"Control","powers":"Zachary Hudson","x":-43.8125,"y":20.34375,"z":4.8125,"marketId":3228943104,"economies":"Agriculture","systemstate":"None"},{"name":"Garratt City","systemName":"LP 291-34","distanceToArrival":157.748052,"type":"Coriolis Starport","allegiance":"Federation","government":"Democracy","economy":"Industrial","faction":"Blood Brothers from Alrai","systemsecurity":"High","systempopulation":7299316,"powerplaystate":"Control","powers":"Zachary Hudson","x":-47.3125,"y":-21.65625,"z":-18.71875,"marketId":3228838144,"economies":"Industrial,Extraction","systemstate":"None"},{"name":"Evans Port","systemName":"Parutis","distanceToArrival":301.865524,"type":"Orbis Starport","allegiance":"Federation","government":"Democracy","economy":"Refinery","faction":"Labour of Parutis","systemsecurity":"High","systempopulation":3893844490,"powerplaystate":"Control","powers":"Zachary Hudson","x":0.71875,"y":10.71875,"z":33.28125,"marketId":3228774144,"economies":"Refinery","systemstate":"None"},{"name":"Mallett Hub","systemName":"Gilgamesh","distanceToArrival":258.617402,"type":"Orbis Starport","allegiance":"Independent","government":"Dictatorship","economy":"Refinery","faction":"Gilgamesh Corps Orbital Protection","systemsecurity":"High","systempopulation":14791691695,"powerplaystate":"Control","powers":"Zachary Hudson","x":-59.875,"y":-16.0,"z":28.78125,"marketId":3228881408,"economies":"Refinery","systemstate":"None"},{"name":"Lindsey Orbital","systemName":"39 Serpentis","distanceToArrival":426.544304,"type":"Orbis Starport","allegiance":"Federation","government":"Democracy","economy":"Agriculture","faction":"Argus Corporation","systemsecurity":"High","systempopulation":6723043084,"powerplaystate":"Control","powers":"Zachary Hudson","x":-16.46875,"y":39.875,"z":36.59375,"marketId":3228920576,"economies":"Agriculture","systemstate":"None"},{"name":"Bunch City","systemName":"Gilgamesh","distanceToArrival":445.67458,"type":"Coriolis Starport","allegiance":"Independent","government":"Dictatorship","economy":"Agriculture","faction":"Gilgamesh Corps Orbital Protection","systemsecurity":"High","systempopulation":14791691695,"powerplaystate":"Control","powers":"Zachary Hudson","x":-59.875,"y":-16.0,"z":28.78125,"marketId":3228880640,"economies":"Agriculture","systemstate":"None"},{"name":"Malerba Station","systemName":"LTT 15449","distanceToArrival":29.634644,"type":"Orbis Starport","allegiance":"Federation","government":"Corporate","economy":"Industrial","faction":"Granthaimi Group","systemsecurity":"High","systempopulation":6791886799,"powerplaystate":"Control","powers":"Zachary Hudson","x":-55.28125,"y":20.5,"z":42.15625,"marketId":3229022464,"economies":"Industrial","systemstate":"None"},{"name":"Clement Station","systemName":"Alpha Fornacis","distanceToArrival":349.647483,"type":"Orbis Starport","allegiance":"Empire","government":"Corporate","economy":"Refinery","faction":"East India Company","systemsecurity":"High","systempopulation":5043700924,"powerplaystate":"Control","powers":"Zachary Hudson","x":16.9375,"y":-39.625,"z":-17.3125,"marketId":3223691008,"economies":"Refinery","systemstate":"Expansion"},{"name":"Lopez de Haro Ring","systemName":"Gilgamesh","distanceToArrival":554.484663,"type":"Orbis Starport","allegiance":"Independent","government":"Dictatorship","economy":"Agriculture","faction":"Gilgamesh Corps Orbital Protection","systemsecurity":"High","systempopulation":14791691695,"powerplaystate":"Control","powers":"Zachary Hudson","x":-59.875,"y":-16.0,"z":28.78125,"marketId":3228880896,"economies":"Agriculture","systemstate":"None"},{"name":"Roddenberry Orbital","systemName":"LHS 3749","distanceToArrival":474.139268,"type":"Coriolis Starport","allegiance":"Federation","government":"Democracy","economy":"Industrial","faction":"Bhotega Labour","systemsecurity":"Medium","systempopulation":5263148,"powerplaystate":"Control","powers":"Zachary Hudson","x":-69.5625,"y":12.46875,"z":-22.4375,"marketId":3226754816,"economies":"Industrial","systemstate":"None"},{"name":"Chilton Vision","systemName":"Onduwatya","distanceToArrival":27.456892,"type":"Coriolis Starport","allegiance":"Independent","government":"Confederacy","economy":"Industrial","faction":"The L.O.S.P.","systemsecurity":"High","systempopulation":25181890,"powerplaystate":"Control","powers":"Zachary Hudson","x":-119.9375,"y":60.34375,"z":-38.71875,"marketId":3226985984,"economies":"Industrial,Extraction","systemstate":"Expansion"},{"name":"Moffitt City","systemName":"Gilgamesh","distanceToArrival":258.476938,"type":"Orbis Starport","allegiance":"Independent","government":"Dictatorship","economy":"Refinery","faction":"Gilgamesh Corps Orbital Protection","systemsecurity":"High","systempopulation":14791691695,"powerplaystate":"Control","powers":"Zachary Hudson","x":-59.875,"y":-16.0,"z":28.78125,"marketId":3228881152,"economies":"Refinery","systemstate":"None"},{"name":"Hardwick Orbital","systemName":"Aornum","distanceToArrival":457901.070572,"type":"Coriolis Starport","allegiance":"Federation","government":"Democracy","economy":"Agriculture","faction":"Aornum Republic Party","systemsecurity":"High","systempopulation":945888291,"powerplaystate":"Control","powers":"Zachary Hudson","x":7.5625,"y":-34.90625,"z":31.625,"marketId":3224227072,"economies":"Agriculture","systemstate":"Boom"},{"name":"Vaucanson Terminal","systemName":"Aornum","distanceToArrival":457915.14663,"type":"Ocellus Starport","allegiance":"Federation","government":"Democracy","economy":"Refinery","faction":"Aornum Republic Party","systemsecurity":"High","systempopulation":945888291,"powerplaystate":"Control","powers":"Zachary Hudson","x":7.5625,"y":-34.90625,"z":31.625,"marketId":3224227584,"economies":"Refinery","systemstate":"Boom"},{"name":"McMonagle Hub","systemName":"Rati Irtii","distanceToArrival":1161.467506,"type":"Ocellus Starport","allegiance":"Federation","government":"Corporate","economy":"Industrial","faction":"Rati Irtii Transport Industries","systemsecurity":"Low","systempopulation":2876325,"powerplaystate":"Control","powers":"Zachary Hudson","x":37.9375,"y":-33.90625,"z":85.1875,"marketId":3226164224,"economies":"Industrial","systemstate":"Boom,Civil Liberty,Public Holiday"},{"name":"Gernsback Terminal","systemName":"Groombridge 1618","distanceToArrival":25.767129,"type":"Orbis Starport","allegiance":"Independent","government":"Dictatorship","economy":"Industrial","faction":"Nationalists of Groombridge 1618","systemsecurity":"High","systempopulation":5914893483,"powerplaystate":"Control","powers":"Zachary Hudson","x":-2.34375,"y":12.625,"z":-9.34375,"marketId":3229019392,"economies":"Industrial","systemstate":"Boom"},{"name":"Crown City","systemName":"Ross 33","distanceToArrival":32.865661,"type":"Ocellus Starport","allegiance":"Federation","government":"Corporate","economy":"Refinery","faction":"Earth Defense Fleet","systemsecurity":"Medium","systempopulation":2764751,"powerplaystate":"Control","powers":"Zachary Hudson","x":0.1875,"y":-8.78125,"z":-28.96875,"marketId":3228031488,"economies":"Refinery,Industrial","systemstate":"Boom,Civil Liberty"},{"name":"de Caminha Station","systemName":"Lushertha","distanceToArrival":366.930888,"type":"Orbis Starport","allegiance":"Federation","government":"Corporate","economy":"Agriculture","faction":"Earth Defense Fleet","systemsecurity":"High","systempopulation":1545531303,"powerplaystate":"Control","powers":"Zachary Hudson","x":-7.09375,"y":2.25,"z":-19.96875,"marketId":3228804352,"economies":"Agriculture","systemstate":"Boom"},{"name":"Tshang Station","systemName":"Lushertha","distanceToArrival":520.382065,"type":"Orbis Starport","allegiance":"Federation","government":"Corporate","economy":"Industrial","faction":"Earth Defense Fleet","systemsecurity":"High","systempopulation":1545531303,"powerplaystate":"Control","powers":"Zachary Hudson","x":-7.09375,"y":2.25,"z":-19.96875,"marketId":3228804608,"economies":"Industrial","systemstate":"Boom"},{"name":"Cook Ring","systemName":"Lushertha","distanceToArrival":697.838803,"type":"Orbis Starport","allegiance":"Federation","government":"Corporate","economy":"Industrial","faction":"Earth Defense Fleet","systemsecurity":"High","systempopulation":1545531303,"powerplaystate":"Control","powers":"Zachary Hudson","x":-7.09375,"y":2.25,"z":-19.96875,"marketId":3228804864,"economies":"Industrial","systemstate":"Boom"},{"name":"Rominger Orbital","systemName":"BD+42 3917","distanceToArrival":281.437281,"type":"Coriolis Starport","allegiance":"Federation","government":"Corporate","economy":"Refinery","faction":"Achelous Smart Industry Corp","systemsecurity":"Medium","systempopulation":196918,"powerplaystate":"Control","powers":"Zachary Hudson","x":-76.53125,"y":-2.21875,"z":7.75,"marketId":3226647040,"economies":"Refinery,Extraction","systemstate":"None"},{"name":"Hogg City","systemName":"Anlave","distanceToArrival":1075.52286,"type":"Coriolis Starport","allegiance":"Independent","government":"Democracy","economy":"High Tech","faction":"C.O.N.T.R.A.I.L","systemsecurity":"Medium","systempopulation":5120288512,"powerplaystate":"Control","powers":"Zachary Hudson","x":-25.375,"y":1.125,"z":-20.84375,"marketId":128128248,"economies":"High Tech,Extraction","systemstate":"Expansion,Pirate Attack"},{"name":"Knight Orbital","systemName":"LHS 6427","distanceToArrival":16.557595,"type":"Ocellus Starport","allegiance":"Federation","government":"Corporate","economy":"Refinery","faction":"LHS 6427 Industry","systemsecurity":"High","systempopulation":12393389,"powerplaystate":"Control","powers":"Zachary Hudson","x":-33.25,"y":-19.78125,"z":-9.53125,"marketId":3228814336,"economies":"Refinery,Industrial","systemstate":"Civil Liberty"},{"name":"Feynman Port","systemName":"Mulungu","distanceToArrival":470.086823,"type":"Coriolis Starport","allegiance":"Independent","government":"Cooperative","economy":"Refinery","faction":"The Independent Nation of Yggdrasil","systemsecurity":"Medium","systempopulation":159903,"powerplaystate":"Control","powers":"Zachary Hudson","x":-36.5,"y":-52.125,"z":12.15625,"marketId":3223963136,"economies":"Refinery,Extraction","systemstate":"None"},{"name":"Dobrovolski City","systemName":"Adeo","distanceToArrival":67.062302,"type":"Orbis Starport","allegiance":"Independent","government":"Feudal","economy":"Refinery","faction":"Marquis du Slavanibo","systemsecurity":"High","systempopulation":8257499087,"powerplaystate":"Control","powers":"Zachary Hudson","x":-81.625,"y":31.40625,"z":27.1875,"marketId":3226846720,"economies":"Refinery","systemstate":"None"},{"name":"Hennen City","systemName":"LHS 1541","distanceToArrival":51.407195,"type":"Orbis Starport","allegiance":"Federation","government":"Anarchy","economy":"Agriculture","faction":"Tauros Mercantile","systemsecurity":"Anarchy","systempopulation":5066988235,"powerplaystate":"Control","powers":"Zachary Hudson","x":-23.78125,"y":-10.8125,"z":-42.53125,"marketId":3228064000,"economies":"Agriculture","systemstate":"None"},{"name":"Naubakht Orbital","systemName":"Epsilon Pavonis","distanceToArrival":4661.421512,"type":"Coriolis Starport","allegiance":"Federation","government":"Corporate","economy":"Industrial","faction":"Damnet Transport Organisation","systemsecurity":"High","systempopulation":5154328,"powerplaystate":"Control","powers":"Zachary Hudson","x":55.09375,"y":-54.65625,"z":70.8125,"marketId":3225375232,"economies":"Industrial","systemstate":"Boom"},{"name":"Feynman Terminal","systemName":"Bhritzameno","distanceToArrival":1374.123754,"type":"Coriolis Starport","allegiance":"Federation","government":"Democracy","economy":"High Tech","faction":"Green Party of Bhritzameno","systemsecurity":"High","systempopulation":18267363,"powerplaystate":"Control","powers":"Zachary Hudson","x":-11.3125,"y":-1.03125,"z":15.34375,"marketId":3228798208,"economies":"High Tech,Refinery","systemstate":"Boom"},{"name":"Pennington City","systemName":"LHS 1541","distanceToArrival":96.12665,"type":"Orbis Starport","allegiance":"Federation","government":"Anarchy","economy":"Agriculture","faction":"Tauros Mercantile","systemsecurity":"Anarchy","systempopulation":5066988235,"powerplaystate":"Control","powers":"Zachary Hudson","x":-23.78125,"y":-10.8125,"z":-42.53125,"marketId":3228064256,"economies":"Agriculture","systemstate":"None"},{"name":"Anning Port","systemName":"LHS 1681","distanceToArrival":570.286577,"type":"Coriolis Starport","allegiance":"Federation","government":"Corporate","economy":"Industrial","faction":"Tharsis Corporation","systemsecurity":"Medium","systempopulation":3174151,"powerplaystate":"Control","powers":"Zachary Hudson","x":-2.46875,"y":-15.78125,"z":-48.40625,"marketId":3228165888,"economies":"Industrial,Refinery","systemstate":"None"},{"name":"Cameron Gateway","systemName":"Wat Yu","distanceToArrival":83.512861,"type":"Coriolis Starport","allegiance":"Independent","government":"Feudal","economy":"Tourism","faction":"Noblemen of LHS 463","systemsecurity":"Low","systempopulation":1178724,"powerplaystate":"Control","powers":"Zachary Hudson","x":-27.09375,"y":6.15625,"z":36.4375,"marketId":3229032192,"economies":"Tourism","systemstate":"None"},{"name":"Foda Station","systemName":"LHS 1541","distanceToArrival":169.456593,"type":"Ocellus Starport","allegiance":"Federation","government":"Anarchy","economy":"Refinery","faction":"Tauros Mercantile","systemsecurity":"Anarchy","systempopulation":5066988235,"powerplaystate":"Control","powers":"Zachary Hudson","x":-23.78125,"y":-10.8125,"z":-42.53125,"marketId":3228065024,"economies":"Refinery","systemstate":"None"},{"name":"McKee Ring","systemName":"GD 219","distanceToArrival":1623.951144,"type":"Coriolis Starport","allegiance":"Federation","government":"Corporate","economy":"High Tech","faction":"Ngolibardu Electronics Solutions","systemsecurity":"Medium","systempopulation":3972954,"powerplaystate":"Control","powers":"Zachary Hudson","x":-48.65625,"y":0.125,"z":41.6875,"marketId":3228921856,"economies":"High Tech,Refinery","systemstate":"Boom"},{"name":"Tanaka Terminal","systemName":"LHS 2088","distanceToArrival":422.647137,"type":"Coriolis Starport","allegiance":"Federation","government":"Democracy","economy":"High Tech","faction":"Union of LHS 2088 Resistance","systemsecurity":"Medium","systempopulation":22390841,"powerplaystate":"Control","powers":"Zachary Hudson","x":-23.3125,"y":25.71875,"z":-28.34375,"marketId":3228232192,"economies":"High Tech,Refinery","systemstate":"Boom,Civil Liberty"},{"name":"Zholobov Gateway","systemName":"Rana","distanceToArrival":1892.345475,"type":"Orbis Starport","allegiance":"Federation","government":"Democracy","economy":"Industrial","faction":"Aegis of Federal Democrats","systemsecurity":"High","systempopulation":17566027075,"powerplaystate":"Control","powers":"Zachary Hudson","x":6.5,"y":-21.0,"z":-19.65625,"marketId":3228832512,"economies":"Industrial","systemstate":"None"},{"name":"Titan City","systemName":"Sol","distanceToArrival":4975.517844,"type":"Orbis Starport","allegiance":"Federation","government":"Democracy","economy":"Refinery","faction":"Mother Gaia","systemsecurity":"High","systempopulation":22780919531,"powerplaystate":"Control","powers":"Zachary Hudson","x":0.0,"y":0.0,"z":0.0,"marketId":128018176,"economies":"Refinery","systemstate":"None"},{"name":"Columbus","systemName":"Sol","distanceToArrival":2652.848487,"type":"Ocellus Starport","allegiance":"Federation","government":"Democracy","economy":"Refinery","faction":"Mother Gaia","systemsecurity":"High","systempopulation":22780919531,"powerplaystate":"Control","powers":"Zachary Hudson","x":0.0,"y":0.0,"z":0.0,"marketId":128017920,"economies":"Refinery","systemstate":"None"},{"name":"Adamson Terminal","systemName":"39 Serpentis","distanceToArrival":425.141072,"type":"Orbis Starport","allegiance":"Federation","government":"Democracy","economy":"Agriculture","faction":"Argus Corporation","systemsecurity":"High","systempopulation":6723043084,"powerplaystate":"Control","powers":"Zachary Hudson","x":-16.46875,"y":39.875,"z":36.59375,"marketId":3228920832,"economies":"Agriculture","systemstate":"None"},{"name":"Suri Park","systemName":"Anlave","distanceToArrival":463.97445,"type":"Coriolis Starport","allegiance":"Independent","government":"Democracy","economy":"High Tech","faction":"C.O.N.T.R.A.I.L","systemsecurity":"Medium","systempopulation":5120288512,"powerplaystate":"Control","powers":"Zachary Hudson","x":-25.375,"y":1.125,"z":-20.84375,"marketId":128127736,"economies":"High Tech","systemstate":"Expansion,Pirate Attack"},{"name":"Bresnik Terminal","systemName":"37 Xi Bootis","distanceToArrival":11860.070401,"type":"Orbis Starport","allegiance":"Federation","government":"Corporate","economy":"Agriculture","faction":"37 Xi Bootis Gold Advanced Ltd","systemsecurity":"High","systempopulation":681717061,"powerplaystate":"Control","powers":"Zachary Hudson","x":-4.21875,"y":19.09375,"z":9.8125,"marketId":3228964608,"economies":"Agriculture","systemstate":"None"},{"name":"Swanwick Enterprise","systemName":"Dongkum","distanceToArrival":16.0,"type":"Ocellus Starport","allegiance":"Independent","government":"Democracy","economy":"Industrial","faction":"Beasts of Bestia","systemsecurity":"High","systempopulation":439405096,"powerplaystate":"Control","powers":"Zachary Hudson","x":-17.875,"y":-11.75,"z":-90.4375,"body":{"id":3826,"id64":0,"bodyId":0,"name":"Dongkum A 3","distanceToArrival":0},"marketId":3228026368,"economies":"Industrial","systemstate":"None"},{"name":"Kobayashi City","systemName":"Anlave","distanceToArrival":280.836557,"type":"Orbis Starport","allegiance":"Independent","government":"Democracy","economy":"High Tech","faction":"C.O.N.T.R.A.I.L","systemsecurity":"Medium","systempopulation":5120288512,"powerplaystate":"Control","powers":"Zachary Hudson","x":-25.375,"y":1.125,"z":-20.84375,"marketId":128127992,"economies":"High Tech,Extraction","systemstate":"Expansion,Pirate Attack"},{"name":"Hahn Ring","systemName":"Dongkum","distanceToArrival":97.302486,"type":"Orbis Starport","allegiance":"Independent","government":"Democracy","economy":"Agriculture","faction":"Beasts of Bestia","systemsecurity":"High","systempopulation":439405096,"powerplaystate":"Control","powers":"Zachary Hudson","x":-17.875,"y":-11.75,"z":-90.4375,"marketId":3228026112,"economies":"Agriculture","systemstate":"None"},{"name":"Lone Rock","systemName":"Othime","distanceToArrival":2.780541,"type":"Asteroid base","allegiance":"Independent","government":"Feudal","economy":"Extraction","faction":"Noblemen of Quilmes","systemsecurity":"Low","systempopulation":44364,"powerplaystate":"Control","powers":"Zachary Hudson","x":2.40625,"y":-26.4375,"z":52.4375,"marketId":128856394,"economies":"Refinery,Extraction","systemstate":"Civil Liberty,Investment"},{"name":"Leavitt Orbital","systemName":"Mombaluma","distanceToArrival":537.14452,"type":"Coriolis Starport","allegiance":"Federation","government":"Corporate","economy":"Refinery","faction":"Gold Universal Co","systemsecurity":"High","systempopulation":6832933,"powerplaystate":"Control","powers":"Zachary Hudson","x":18.875,"y":-15.84375,"z":22.03125,"marketId":3228593920,"economies":"Refinery,Industrial","systemstate":"Boom"},{"name":"Nusslein-Volhard Terminal","systemName":"NLTT 46621","distanceToArrival":1255.46853,"type":"Orbis Starport","allegiance":"Independent","government":"Theocracy","economy":"Tourism","faction":"The Link","systemsecurity":"High","systempopulation":4647443345,"powerplaystate":"Control","powers":"Zachary Hudson","x":-43.8125,"y":20.34375,"z":4.8125,"marketId":3228943360,"economies":"Tourism","systemstate":"None"},{"name":"Fort Dixon","systemName":"Vega","distanceToArrival":3751.863144,"type":"Orbis Starport","allegiance":"Federation","government":"Democracy","economy":"Agriculture","faction":"Vega Independents","systemsecurity":"High","systempopulation":600017409,"powerplaystate":"Control","powers":"Zachary Hudson","x":-21.90625,"y":8.125,"z":9.0,"marketId":128149496,"economies":"Agriculture","systemstate":"None"},{"name":"Mawson Oasis","systemName":"Phanes","distanceToArrival":340.246218,"type":"Orbis Starport","allegiance":"Independent","government":"Dictatorship","economy":"Agriculture","faction":"Civitas Dei","systemsecurity":"Medium","systempopulation":1783752,"powerplaystate":"Control","powers":"Zachary Hudson","x":10.5,"y":25.28125,"z":-47.34375,"marketId":128096248,"economies":"Agriculture","systemstate":"None"},{"name":"Leiber Installation","systemName":"Phanes","distanceToArrival":339.667675,"type":"Coriolis Starport","allegiance":"Independent","government":"Dictatorship","economy":"Refinery","faction":"Civitas Dei","systemsecurity":"Medium","systempopulation":1783752,"powerplaystate":"Control","powers":"Zachary Hudson","x":10.5,"y":25.28125,"z":-47.34375,"marketId":128096504,"economies":"Refinery","systemstate":"None"},{"name":"Hahn Gateway","systemName":"Nanomam","distanceToArrival":398.352397,"type":"Orbis Starport","allegiance":"Federation","government":"Corporate","economy":"Agriculture","faction":"Earth Defense Fleet","systemsecurity":"High","systempopulation":2121852318,"powerplaystate":"Control","powers":"Zachary Hudson","x":-14.78125,"y":19.65625,"z":-15.25,"marketId":3228793344,"economies":"Agriculture","systemstate":"None"},{"name":"Vinci Hub","systemName":"Adeo","distanceToArrival":327.28112,"type":"Orbis Starport","allegiance":"Independent","government":"Feudal","economy":"Agriculture","faction":"Marquis du Slavanibo","systemsecurity":"High","systempopulation":8257499087,"powerplaystate":"Control","powers":"Zachary Hudson","x":-81.625,"y":31.40625,"z":27.1875,"marketId":3226846464,"economies":"Agriculture","systemstate":"None"},{"name":"Bonkers","systemName":"Wolf 25","distanceToArrival":285.98367,"type":"Coriolis Starport","allegiance":"Independent","government":"Cooperative","economy":"Agriculture","faction":"Hutton Orbital Truckers Co-Operative","systemsecurity":"Medium","systempopulation":1317590,"powerplaystate":"Control","powers":"Zachary Hudson","x":-11.0625,"y":-20.46875,"z":-7.125,"marketId":128124408,"economies":"Agriculture","systemstate":"Boom,Civil Liberty"},{"name":"von Biela Dock","systemName":"Clayahu","distanceToArrival":462.683732,"type":"Ocellus Starport","allegiance":"Empire","government":"Corporate","economy":"Industrial","faction":"Daily Routine Incorporated","systemsecurity":"High","systempopulation":7734677,"powerplaystate":"Control","powers":"Zachary Hudson","x":82.96875,"y":-76.0625,"z":37.21875,"marketId":3223793664,"economies":"Industrial,Extraction","systemstate":"Boom"},{"name":"M.Gorbachev","systemName":"Sol","distanceToArrival":505.440427,"type":"Orbis Starport","allegiance":"Federation","government":"Democracy","economy":"Service","faction":"Mother Gaia","systemsecurity":"High","systempopulation":22780919531,"powerplaystate":"Control","powers":"Zachary Hudson","x":0.0,"y":0.0,"z":0.0,"marketId":128017152,"economies":"Service","systemstate":"None"},{"name":"Galileo","systemName":"Sol","distanceToArrival":506.928138,"type":"Ocellus Starport","allegiance":"Federation","government":"Democracy","economy":"Refinery","faction":"Mother Gaia","systemsecurity":"High","systempopulation":22780919531,"powerplaystate":"Control","powers":"Zachary Hudson","x":0.0,"y":0.0,"z":0.0,"marketId":128016640,"economies":"Refinery","systemstate":"None"},{"name":"Li Qing Jao","systemName":"Sol","distanceToArrival":505.47231,"type":"Orbis Starport","allegiance":"Federation","government":"Democracy","economy":"Service","faction":"Federal Congress","systemsecurity":"High","systempopulation":22780919531,"powerplaystate":"Control","powers":"Zachary Hudson","x":0.0,"y":0.0,"z":0.0,"marketId":128017408,"economies":"Service","systemstate":"None"},{"name":"Mars High","systemName":"Sol","distanceToArrival":766.320603,"type":"Orbis Starport","allegiance":"Federation","government":"Democracy","economy":"Service","faction":"Sol Workers' Party","systemsecurity":"High","systempopulation":22780919531,"powerplaystate":"Control","powers":"Zachary Hudson","x":0.0,"y":0.0,"z":0.0,"marketId":128017664,"economies":"Service","systemstate":"None"},{"name":"Abraham Lincoln","systemName":"Sol","distanceToArrival":505.645946,"type":"Orbis Starport","allegiance":"Federation","government":"Democracy","economy":"Service","faction":"Mother Gaia","systemsecurity":"High","systempopulation":22780919531,"powerplaystate":"Control","powers":"Zachary Hudson","x":0.0,"y":0.0,"z":0.0,"marketId":128016896,"economies":"Service","systemstate":"None"},{"name":"Gantt Station","systemName":"14 Geminorum","distanceToArrival":1099.43131,"type":"Coriolis Starport","allegiance":"Independent","government":"Democracy","economy":"Industrial","faction":"Flotta Stellare","systemsecurity":"High","systempopulation":36586522,"powerplaystate":"Control","powers":"Zachary Hudson","x":12.28125,"y":5.0625,"z":-57.25,"marketId":3228082688,"economies":"Industrial,Extraction","systemstate":"None"},{"name":"Kovalevsky Dock","systemName":"NLTT 46403","distanceToArrival":276104.351951,"type":"Ocellus Starport","allegiance":"Alliance","government":"Patronage","economy":"Industrial","faction":"Tai Qing Alliance Bond","systemsecurity":"Medium","systempopulation":1693649,"powerplaystate":"Control","powers":"Zachary Hudson","x":-101.71875,"y":43.46875,"z":45.71875,"marketId":3226861056,"economies":"Industrial","systemstate":"None"},{"name":"Teng-hui Hub","systemName":"Parutis","distanceToArrival":503.236716,"type":"Orbis Starport","allegiance":"Federation","government":"Corporate","economy":"Refinery","faction":"Parutis Corp.","systemsecurity":"High","systempopulation":3893844490,"powerplaystate":"Control","powers":"Zachary Hudson","x":0.71875,"y":10.71875,"z":33.28125,"marketId":3228774400,"economies":"Refinery","systemstate":"None"},{"name":"Braun Station","systemName":"Gliese 868","distanceToArrival":78.044378,"type":"Coriolis Starport","allegiance":"Federation","government":"Corporate","economy":"Extraction","faction":"LP 932-12 Dynamic Inc","systemsecurity":"High","systempopulation":8508724066,"powerplaystate":"Control","powers":"Zachary Hudson","x":-7.375,"y":-38.96875,"z":19.5,"marketId":3224117504,"economies":"Extraction","systemstate":"Boom"},{"name":"Binney Dock","systemName":"Caspatsuria","distanceToArrival":370.29112,"type":"Coriolis Starport","allegiance":"Independent","government":"Democracy","economy":"High Tech","faction":"Revolutionary Jotunheim Resistance","systemsecurity":"High","systempopulation":11931312,"powerplaystate":"Control","powers":"Zachary Hudson","x":63.5,"y":-116.90625,"z":48.15625,"marketId":3222967040,"economies":"High Tech,Extraction","systemstate":"Boom,Expansion"},{"name":"Taylor City","systemName":"Vega","distanceToArrival":1083.185648,"type":"Orbis Starport","allegiance":"Federation","government":"Democracy","economy":"Agriculture","faction":"Vega Independents","systemsecurity":"High","systempopulation":600017409,"powerplaystate":"Control","powers":"Zachary Hudson","x":-21.90625,"y":8.125,"z":9.0,"marketId":128149240,"economies":"Agriculture","systemstate":"None"},{"name":"Haller Port","systemName":"LHS 1541","distanceToArrival":70.11926,"type":"Orbis Starport","allegiance":"Federation","government":"Anarchy","economy":"Refinery","faction":"Tauros Mercantile","systemsecurity":"Anarchy","systempopulation":5066988235,"powerplaystate":"Control","powers":"Zachary Hudson","x":-23.78125,"y":-10.8125,"z":-42.53125,"marketId":3228064512,"economies":"Refinery","systemstate":"None"},{"name":"Bacon Port","systemName":"Gliese 868","distanceToArrival":28.343689,"type":"Coriolis Starport","allegiance":"Federation","government":"Corporate","economy":"Extraction","faction":"Izumo Heavy Industries Ltd","systemsecurity":"High","systempopulation":8508724066,"powerplaystate":"Control","powers":"Zachary Hudson","x":-7.375,"y":-38.96875,"z":19.5,"marketId":3224116736,"economies":"Extraction","systemstate":"Boom"},{"name":"Smith Port","systemName":"LTT 9795","distanceToArrival":2488.265795,"type":"Ocellus Starport","allegiance":"Independent","government":"Democracy","economy":"Industrial","faction":"Paladin Consortium","systemsecurity":"High","systempopulation":5638022,"powerplaystate":"Control","powers":"Zachary Hudson","x":5.75,"y":-68.875,"z":18.90625,"marketId":3224007168,"economies":"Industrial,Refinery","systemstate":"None"},{"name":"MacLean Terminal","systemName":"Gliese 868","distanceToArrival":36.964091,"type":"Coriolis Starport","allegiance":"Federation","government":"Corporate","economy":"Extraction","faction":"Izumo Heavy Industries Ltd","systemsecurity":"High","systempopulation":8508724066,"powerplaystate":"Control","powers":"Zachary Hudson","x":-7.375,"y":-38.96875,"z":19.5,"marketId":3224116992,"economies":"Extraction","systemstate":"Boom"},{"name":"Hopkins Landing","systemName":"Lung","distanceToArrival":91.200377,"type":"Coriolis Starport","allegiance":"Federation","government":"Democracy","economy":"Refinery","faction":"Green Party of Lung","systemsecurity":"Medium","systempopulation":625972,"powerplaystate":"Control","powers":"Zachary Hudson","x":3.71875,"y":-6.53125,"z":-13.53125,"marketId":3228781056,"economies":"Refinery,Extraction","systemstate":"Boom,Civil Liberty"},{"name":"Grechko Dock","systemName":"Abi","distanceToArrival":41.903977,"type":"Coriolis Starport","allegiance":"Federation","government":"Confederacy","economy":"Industrial","faction":"Tibis Alliance","systemsecurity":"High","systempopulation":11834159,"powerplaystate":"Control","powers":"Zachary Hudson","x":-32.34375,"y":-29.90625,"z":10.625,"marketId":3224082688,"economies":"Industrial,Extraction","systemstate":"Boom"},{"name":"Ali Hub","systemName":"Rana","distanceToArrival":670.417921,"type":"Coriolis Starport","allegiance":"Federation","government":"Corporate","economy":"Agriculture","faction":"Earth Defense Fleet","systemsecurity":"High","systempopulation":17566027075,"powerplaystate":"Control","powers":"Zachary Hudson","x":6.5,"y":-21.0,"z":-19.65625,"marketId":3228832256,"economies":"Agriculture","systemstate":"None"},{"name":"Mullane Hub","systemName":"Rana","distanceToArrival":3721.570973,"type":"Coriolis Starport","allegiance":"Federation","government":"Corporate","economy":"Industrial","faction":"Earth Defense Fleet","systemsecurity":"High","systempopulation":17566027075,"powerplaystate":"Control","powers":"Zachary Hudson","x":6.5,"y":-21.0,"z":-19.65625,"marketId":3228833024,"economies":"Industrial","systemstate":"None"},{"name":"Wescott Hub","systemName":"Rana","distanceToArrival":2884.642888,"type":"Orbis Starport","allegiance":"Federation","government":"Corporate","economy":"Industrial","faction":"Earth Defense Fleet","systemsecurity":"High","systempopulation":17566027075,"powerplaystate":"Control","powers":"Zachary Hudson","x":6.5,"y":-21.0,"z":-19.65625,"marketId":3228832768,"economies":"Industrial","systemstate":"None"},{"name":"Popovich Hub","systemName":"Epsilon Scorpii","distanceToArrival":584.741122,"type":"Orbis Starport","allegiance":"Independent","government":"Corporate","economy":"Industrial","faction":"Epsilon Scorpii Inc","systemsecurity":"High","systempopulation":7936392052,"powerplaystate":"Control","powers":"Zachary Hudson","x":11.875,"y":6.625,"z":62.21875,"marketId":3230487040,"economies":"Industrial","systemstate":"None"},{"name":"Daedalus","systemName":"Sol","distanceToArrival":158.744926,"type":"Orbis Starport","allegiance":"Federation","government":"Democracy","economy":"Refinery","faction":"Mother Gaia","systemsecurity":"High","systempopulation":22780919531,"powerplaystate":"Control","powers":"Zachary Hudson","x":0.0,"y":0.0,"z":0.0,"marketId":128016384,"economies":"Refinery","systemstate":"None"},{"name":"Gresley Dock","systemName":"Nanomam","distanceToArrival":398.741005,"type":"Orbis Starport","allegiance":"Federation","government":"Corporate","economy":"Agriculture","faction":"Earth Defense Fleet","systemsecurity":"High","systempopulation":2121852318,"powerplaystate":"Control","powers":"Zachary Hudson","x":-14.78125,"y":19.65625,"z":-15.25,"marketId":3228793088,"economies":"Agriculture","systemstate":"None"}]